pagify/__init__.py
pagify/adapters/__init__.py
pagify/adapters/paginate.py
pagify/core/__init__.py
pagify/core/cursor_paginator.py
pagify/core/offset_paginator.py
pagify/core/page_number_paginator.py
pagify/tests/__init__.py
pagify/tests/test_paginate.py
pagify/utils/__init__.py
pagify/utils/response_formatting.py
pagify/utils/serializer.py
pagify-1.1.1.dist-info/METADATA
pagify-1.1.1.dist-info/WHEEL
pagify-1.1.1.dist-info/top_level.txt
pagify-1.1.1.dist-info/RECORD
