Metadata-Version: 2.1
Name: pagify
Version: 1.1.1
Summary: A lightweight and flexible pagination package for Python applications.
Home-page: https://github.com/Mohammad222PR/pagify
Author: Mohammad Eslami
Keywords: pagination python api adapter utilities
Classifier: Programming Language :: Python :: 3
Classifier: License :: OSI Approved :: MIT License
Classifier: Operating System :: OS Independent
Classifier: Development Status :: 3 - Alpha
Classifier: Intended Audience :: Developers
Classifier: Topic :: Software Development :: Libraries :: Python Modules
Requires-Python: >=3.6
